{
  "id": "drp-devendor",
  "name": "drp-devendor",
  "title": "deep-research-pro: 清除 vendored 残留并对齐文档与版本",
  "description": "",
  "status": "completed",
  "dev_type": null,
  "scope": null,
  "package": null,
  "priority": "P2",
  "creator": "lyh",
  "assignee": "lyh",
  "createdAt": "2026-06-20",
  "completedAt": "2026-06-20",
  "branch": null,
  "base_branch": "main",
  "worktree_path": null,
  "commit": null,
  "pr_url": null,
  "subtasks": [],
  "children": [],
  "parent": "06-20-rlk-skills-optimization",
  "relatedFiles": [],
  "notes": "",
  "meta": {}
}